{
  "formatVersion": 1,
  "database": {
    "version": 3,
    "identityHash": "0f4c519a4f1a3fa4ee1bfc305322f34f",
    "entities": [
      {
        "tableName": "project_table",
        "createSql": "CREATE TABLE IF NOT EXISTS `${TABLE_NAME}` (`id` INTEGER NOT NULL, `name` TEXT NOT NULL, `slug` TEXT NOT NULL, `myPermissions` TEXT NOT NULL, `isEpicsActivated` INTEGER NOT NULL, `isBacklogActivated` INTEGER NOT NULL, `isKanbanActivated` INTEGER NOT NULL, `isIssuesActivated` INTEGER NOT NULL, `isWikiActivated` INTEGER NOT NULL, `defaultSwimlane` INTEGER, `isAdmin` INTEGER NOT NULL DEFAULT false, `isMember` INTEGER NOT NULL DEFAULT false, `isOwner` INTEGER NOT NULL DEFAULT false, `description` TEXT NOT NULL DEFAULT '', `avatarUrl` TEXT, PRIMARY KEY(`id`))",
        "fields": [
          {
            "fieldPath": "id",
            "columnName": "id",
            "affinity": "INTEGER",
            "notNull": true
          },
          {
            "fieldPath": "name",
            "columnName": "name",
            "affinity": "TEXT",
            "notNull": true
          },
          {
            "fieldPath": "slug",
            "columnName": "slug",
            "affinity": "TEXT",
            "notNull": true
          },
          {
            "fieldPath": "myPermissions",
            "columnName": "myPermissions",
            "affinity": "TEXT",
            "notNull": true
          },
          {
            "fieldPath": "isEpicsActivated",
            "columnName": "isEpicsActivated",
            "affinity": "INTEGER",
            "notNull": true
          },
          {
            "fieldPath": "isBacklogActivated",
            "columnName": "isBacklogActivated",
            "affinity": "INTEGER",
            "notNull": true
          },
          {
            "fieldPath": "isKanbanActivated",
            "columnName": "isKanbanActivated",
            "affinity": "INTEGER",
            "notNull": true
          },
          {
            "fieldPath": "isIssuesActivated",
            "columnName": "isIssuesActivated",
            "affinity": "INTEGER",
            "notNull": true
          },
          {
            "fieldPath": "isWikiActivated",
            "columnName": "isWikiActivated",
            "affinity": "INTEGER",
            "notNull": true
          },
          {
            "fieldPath": "defaultSwimlane",
            "columnName": "defaultSwimlane",
            "affinity": "INTEGER"
          },
          {
            "fieldPath": "isAdmin",
            "columnName": "isAdmin",
            "affinity": "INTEGER",
            "notNull": true,
            "defaultValue": "false"
          },
          {
            "fieldPath": "isMember",
            "columnName": "isMember",
            "affinity": "INTEGER",
            "notNull": true,
            "defaultValue": "false"
          },
          {
            "fieldPath": "isOwner",
            "columnName": "isOwner",
            "affinity": "INTEGER",
            "notNull": true,
            "defaultValue": "false"
          },
          {
            "fieldPath": "description",
            "columnName": "description",
            "affinity": "TEXT",
            "notNull": true,
            "defaultValue": "''"
          },
          {
            "fieldPath": "avatarUrl",
            "columnName": "avatarUrl",
            "affinity": "TEXT"
          }
        ],
        "primaryKey": {
          "autoGenerate": false,
          "columnNames": [
            "id"
          ]
        }
      }
    ],
    "setupQueries": [
      "CREATE TABLE IF NOT EXISTS room_master_table (id INTEGER PRIMARY KEY,identity_hash TEXT)",
      "INSERT OR REPLACE INTO room_master_table (id,identity_hash) VALUES(42, '0f4c519a4f1a3fa4ee1bfc305322f34f')"
    ]
  }
}